testsuite/__init__.py
testsuite/clean_xml.py
testsuite/console.py
testsuite/constants.py
testsuite/generate_sch.py
testsuite/tests/test_generate_sch.py
testsuite/tests/test_validate_sch.py
testsuite/validate_sch.py
testsuite-0.1.5.dist-info/METADATA
testsuite-0.1.5.dist-info/WHEEL
testsuite-0.1.5.dist-info/entry_points.txt
testsuite-0.1.5.dist-info/licenses/AUTHORS.md
testsuite-0.1.5.dist-info/licenses/LICENSE.txt
testsuite-0.1.5.dist-info/RECORD
