Metadata-Version: 2.4
Name: testsuite
Version: 0.1.5
Summary: Example BuildingSync files and tools for writing and validating BuildingSync use cases as schematron files.
License: BSD4
License-File: AUTHORS.md
License-File: LICENSE.txt
Keywords: BuildingSync,Building Data Exchange,Schematron
Author: Ted Summer
Author-email: ted@devetry.com
Requires-Python: >=3.9,<4.0
Classifier: Development Status :: 4 - Beta
Classifier: Environment :: Console
Classifier: Intended Audience :: Developers
Classifier: Intended Audience :: Science/Research
Classifier: License :: Other/Proprietary License
Classifier: Programming Language :: Python :: 3
Classifier: Programming Language :: Python :: 3.9
Classifier: Programming Language :: Python :: 3.10
Classifier: Programming Language :: Python :: 3.11
Classifier: Programming Language :: Python :: 3.12
Classifier: Programming Language :: Python :: 3.13
Classifier: Programming Language :: Python :: 3.14
Classifier: Topic :: Scientific/Engineering
Requires-Dist: lxml (>=5.3.0,<6.0.0)
Project-URL: Documentation, https://github.com/BuildingSync/TestSuite
Project-URL: Homepage, https://buildingsync.net
Project-URL: Repository, https://github.com/BuildingSync/TestSuite
